{ 
    "tasks" : [
        {
            "id": 1,
            "text": "Task 1",
            "day": "Day 1",
            "reminder": true
        },
        {
            "id": 2,
            "text": "Task 2",
            "day": "Day 2",
            "reminder": false
        },
        {
            "id": 3,
            "text": "Task 3",
            "day": "Day 3",
            "reminder": true
        },
        {
            "id": 4,
            "text": "Task 4",
            "day": "Day 4",
            "reminder": false
        },
        {
            "id": 5,
            "text": "Task 5",
            "day": "Day 5",
            "reminder": true
        }
    ]
}